pymorton/__init__.py
pymorton-1.0.5.dist-info/DESCRIPTION.rst
pymorton-1.0.5.dist-info/METADATA
pymorton-1.0.5.dist-info/RECORD
pymorton-1.0.5.dist-info/WHEEL
pymorton-1.0.5.dist-info/metadata.json
pymorton-1.0.5.dist-info/top_level.txt
