Metadata-Version: 2.0
Name: pymorton
Version: 1.0.5
Summary: A lightweight morton coder with lat/long support.
Home-page: https://github.com/trevorprater/pymorton
Author: Trevor Prater
Author-email: trevor.prater@gmail.com
License: MIT
Keywords: nearest neighbors,geo hashing,geo,z-order,morton coding,hashing
Platform: UNKNOWN
Classifier: Development Status :: 5 - Production/Stable
Classifier: Topic :: Utilities
Classifier: License :: OSI Approved :: MIT License
Requires-Python: >=2.6
